migration_docs/__init__.py
migration_docs/apps.py
migration_docs/core.py
migration_docs/management/__init__.py
migration_docs/management/commands/__init__.py
migration_docs/management/commands/migration_docs.py
migration_docs/utils.py
migration_docs/version.py
django_migration_docs-1.4.0.dist-info/LICENSE
django_migration_docs-1.4.0.dist-info/METADATA
django_migration_docs-1.4.0.dist-info/WHEEL
django_migration_docs-1.4.0.dist-info/RECORD
