Metadata-Version: 2.1
Name: django-migration-docs
Version: 1.4.0
Summary: Sync and validate additional information about your Django migrations.
Home-page: https://github.com/Opus10/django-migration-docs
License: BSD-3-Clause
Author: Juliana de Heer
Requires-Python: >=3.9.0,<4
Classifier: Framework :: Django
Classifier: Framework :: Django :: 4.2
Classifier: Framework :: Django :: 5.0
Classifier: Framework :: Django :: 5.1
Classifier: Intended Audience :: Developers
Classifier: License :: OSI Approved :: BSD License
Classifier: Operating System :: OS Independent
Classifier: Programming Language :: Python
Classifier: Programming Language :: Python :: 3
Classifier: Programming Language :: Python :: 3.9
Classifier: Programming Language :: Python :: 3.10
Classifier: Programming Language :: Python :: 3.11
Classifier: Programming Language :: Python :: 3.12
Classifier: Programming Language :: Python :: 3.13
Classifier: Programming Language :: Python :: 3 :: Only
Requires-Dist: django (>=4)
Requires-Dist: formaldict (>=1.0.0)
Requires-Dist: jinja2 (>=2.11.3)
Requires-Dist: pyyaml (>=5.4)
Project-URL: Documentation, https://django-migration-docs.readthedocs.io
Project-URL: Repository, https://github.com/Opus10/django-migration-docs
